{
  "slug": "angry-hornet",
  "nom": "Frelon Furieux",
  "nom_original": "Angry Hornet",
  "categorie": "autre",
  "rarete": "peu_commun",
  "harmonisation": false,
  "harmonisation_detail": null,
  "type": "autre",
  "effets": [],
  "poids": "0.000",
  "prix_estime": "0.00",
  "source": "SRD",
  "image": null,
  "resume": "Munition magique qui se multiplie en vol, créant 2d4 projectiles supplémentaires vers la cible.",
  "combat": {
    "bonus": 0,
    "bonus_ca": 0,
    "degats_bonus": "",
    "type_degats_bonus": "",
    "pv_soins": "",
    "charges": null,
    "effets": [
      "Se multiplie en 2d4 munitions identiques en vol",
      "Jets d'attaque séparés pour chaque projectile",
      "Si tous les projectiles manquent, la munition originale reste magique et peut être tirée de nouveau"
    ]
  }
}