{
  "slug": "armor-of-the-ngobou",
  "nom": "Armure de the Ngobou",
  "nom_original": "Armor of the Ngobou",
  "categorie": "armure_magique",
  "rarete": "rare",
  "harmonisation": true,
  "harmonisation_detail": null,
  "type": "armure_magique",
  "description": "This thick and rough armor is made from the hide of a Ngobou (see Tome of Beasts), an aggressive, ox-sized dinosaur known to threaten elephants of the plains. The horns and tusks of the dinosaur are worked into the armor as spiked shoulder pads. While wearing this armor, you gain a +1 bonus to AC, and you have a magical sense for elephants. You automatically detect if an elephant has passed within 90 feet of your location within the last 24 hours, and you have advantage on any Wisdom (Perception) or Wisdom (Survival) checks you make to find elephants.",
  "effets": [],
  "poids": "12.000",
  "prix_estime": "0.00",
  "source": "SRD",
  "image": null
}