{
  "slug": "aurochs-bracers",
  "nom": "Aurochs Bracers",
  "nom_original": "Aurochs Bracers",
  "categorie": "objet_merveilleux",
  "rarete": "peu_commun",
  "harmonisation": true,
  "harmonisation_detail": null,
  "type": "objet_merveilleux",
  "description": "These bracers have the graven image of a bull's head on them. Your Strength score is 19 while you wear these bracers. It has no effect on you if your Strength is already 19 or higher. In addition, when you use the Attack action to shove a creature, you have advantage on the Strength (Athletics) check.",
  "description_fr": "Ces brassards portent l'image gravée d'une tête de taureau. Votre valeur de Force est 19 tant que vous les portez. Si votre Force est déjà 19 ou plus, cela n'a aucun effet. De plus, lorsque vous utilisez l'action Attaquer pour bousculer une créature, vous avez l'avantage au test de Force (Athlétisme).",
  "effets": [],
  "poids": "0.000",
  "prix_estime": "0.00",
  "source": "SRD",
  "image": null
}