{
  "slug": "cap-of-thorns",
  "nom": "Couronne d'Épines",
  "nom_original": "Cap of Thorns",
  "categorie": "objet_merveilleux",
  "rarete": "tres_rare",
  "harmonisation": true,
  "harmonisation_detail": null,
  "type": "objet_merveilleux",
  "effets": [],
  "poids": "0.000",
  "prix_estime": "0.00",
  "source": "SRD",
  "image": null,
  "resume": "Cercle épineux qui se fusionne au cuir chevelu et inflige des dégâts réguliers, mais permet de lancer un sort d'enchevêtrement avec charme-personne une fois par jour.",
  "combat": {
    "bonus": 0,
    "bonus_ca": 0,
    "degats_bonus": "2d4 à la mise en place, 1d4 par jour",
    "type_degats_bonus": "perforant",
    "pv_soins": "",
    "charges": 1,
    "effets": [
      "Inflige 2d4 dégâts perforants à la mise en place, puis 1d4 chaque jour",
      "1/jour : sacrifier 1 PV par niveau pour enchevêtrement + charme-personne (jet sauvegarde Charisme)",
      "Charme permanent après 3 échecs consécutifs au jet de sauvegarde"
    ]
  }
}