{
  "slug": "cube-of-force",
  "nom": "Cube de force",
  "nom_original": "Cube of Force",
  "categorie": "objet_merveilleux",
  "rarete": "rare",
  "harmonisation": true,
  "harmonisation_detail": null,
  "type": "objet_merveilleux",
  "effets": [],
  "poids": "0.000",
  "prix_estime": "0.00",
  "source": "SRD",
  "image": null,
  "resume": "Cube créant une barrière de force cubique de 4,5 m centrée sur vous selon la face activée, bloquant gaz, matière non vivante, créatures vivantes, sorts ou tout.",
  "combat": {
    "bonus": 0,
    "bonus_ca": 0,
    "degats_bonus": "",
    "type_degats_bonus": "",
    "pv_soins": "",
    "charges": 36,
    "effets": [
      "Barrière de force cubique 4,5 m (durée 1 min, se déplace avec vous)",
      "6 faces : gaz (1), matière inanimée (2), créatures vivantes (3), sorts (4), tout (5), désactivation (0)",
      "Récupère 1d20 charges à l'aube; perte charges face à certains sorts"
    ]
  }
}