{
  "slug": "dragonstooth-blade",
  "nom": "Lame de Croc de Dragon",
  "nom_original": "Dragonstooth Blade",
  "categorie": "arme_magique",
  "rarete": "tres_rare",
  "harmonisation": true,
  "harmonisation_detail": null,
  "type": "arme_magique",
  "effets": [],
  "poids": "0.000",
  "prix_estime": "0.00",
  "source": "SRD",
  "image": null,
  "resume": "Épée magique infligeant 1d6 dégâts supplémentaires du type associé à sa dent de dragon et conférant une résistance à ce type.",
  "combat": {
    "bonus": 0,
    "bonus_ca": 0,
    "degats_bonus": "1d6",
    "type_degats_bonus": "acide, feu, poison, foudre, froid ou nécrotique",
    "pv_soins": "",
    "charges": null,
    "effets": [
      "1d6 dégâts supplémentaires du type associé au dragon",
      "Résistance au type de dégâts du dragon source"
    ]
  }
}