{
  "slug": "helm-of-the-slashing-fin",
  "nom": "Heaume de la Nageoire Tranchante",
  "nom_original": "Helm of the Slashing Fin",
  "categorie": "objet_merveilleux",
  "rarete": "peu_commun",
  "harmonisation": true,
  "harmonisation_detail": null,
  "type": "objet_merveilleux",
  "effets": [],
  "poids": "0.000",
  "prix_estime": "0.00",
  "source": "SRD",
  "image": null,
  "resume": "Ce heaume permet de respirer sous l'eau au lieu de l'air en prononçant un mot de commande.",
  "combat": {
    "bonus": 0,
    "bonus_ca": 0,
    "degats_bonus": "",
    "type_degats_bonus": "",
    "pv_soins": "",
    "charges": null,
    "effets": [
      "Respiration aquatique (mot de commande)",
      "Perte de respiration aérienne lors de l'activation"
    ]
  }
}