{
  "slug": "labrys-of-the-raging-bull-greataxe",
  "nom": "Labrys of the Raging Bull (Greataxe)",
  "nom_original": "Labrys of the Raging Bull (Greataxe)",
  "categorie": "arme_magique",
  "rarete": "rare",
  "harmonisation": false,
  "harmonisation_detail": null,
  "type": "arme_magique",
  "description": "You gain a +1 bonus to attack and damage rolls made with this magic weapon. While you wield the axe, you have advantage on Strength (Athletics) checks to shove a creature, and you can shove a creature up to two sizes larger than you.",
  "effets": [],
  "poids": "0.000",
  "prix_estime": "0.00",
  "source": "SRD",
  "image": null
}