{
  "slug": "manual-of-vine-golem",
  "nom": "Manuel du Golem de Lianes",
  "nom_original": "Manual of Vine Golem",
  "categorie": "objet_merveilleux",
  "rarete": "tres_rare",
  "harmonisation": false,
  "harmonisation_detail": null,
  "type": "objet_merveilleux",
  "effets": [],
  "poids": "0.000",
  "prix_estime": "0.00",
  "source": "SRD",
  "image": null,
  "resume": "Tome permettant à un druide de créer un Golem de Lianes après 20 jours de travail et 30 000 po de composants. Le golem devient alors sous son contrôle permanent.",
  "combat": {
    "bonus": 0,
    "bonus_ca": 0,
    "degats_bonus": "",
    "type_degats_bonus": "",
    "pv_soins": "",
    "charges": null,
    "effets": [
      "Création d'un golem de lianes sous contrôle du druide",
      "Nécessite 20 jours de travail ininterrompu",
      "Les non-druides prenant 4d6 dégâts psychiques en le lisant"
    ]
  }
}