{
  "slug": "moonfield-lens",
  "nom": "Lentille de Champ Lunaire",
  "nom_original": "Moonfield Lens",
  "categorie": "objet_merveilleux",
  "rarete": "tres_rare",
  "harmonisation": true,
  "harmonisation_detail": null,
  "type": "objet_merveilleux",
  "effets": [],
  "poids": "0.000",
  "prix_estime": "0.00",
  "source": "SRD",
  "image": null,
  "resume": "Lentille magique avec 4 charges (récupère 1d3+1 à l'aube) permettant de localiser un être cher ou de naviguer automatiquement en wilderness pendant 1 heure.",
  "combat": {
    "bonus": 0,
    "bonus_ca": 0,
    "degats_bonus": "",
    "type_degats_bonus": "",
    "pv_soins": "",
    "charges": 4,
    "effets": [
      "Localiser un être cher (2 charges)",
      "Navigation automatique 1h ou trouver la surface (2 charges)",
      "Récupère 1d3+1 charges à l'aube"
    ]
  }
}