{
  "slug": "orb-of-obfuscation",
  "nom": "Sphère d'Obscurcissement",
  "nom_original": "Orb of Obfuscation",
  "categorie": "potion",
  "rarete": "peu_commun",
  "harmonisation": false,
  "harmonisation_detail": null,
  "type": "potion",
  "effets": [],
  "poids": "0.000",
  "prix_estime": "0.00",
  "source": "SRD",
  "image": null,
  "resume": "Orbe céramique contenant des produits chimiques magiques qui créent un nuage opaque de gaz gris obscurcissant massivement et amortissant les sons dans un rayon de 30 pieds.",
  "combat": {
    "bonus": 0,
    "bonus_ca": 0,
    "degats_bonus": "",
    "type_degats_bonus": "",
    "pv_soins": "",
    "charges": 1,
    "effets": [
      "Zone obscurcie : sphère de 30 pieds d'obscurité totale et encombrement",
      "Amortissement sonore : audition limitée à 5 pieds de distance",
      "Durée : 5 minutes ou jusqu'à une rafale de vent modéré"
    ]
  }
}