{
  "slug": "rod-of-the-wastes",
  "nom": "Sceptre des Terres Stériles",
  "nom_original": "Rod of the Wastes",
  "categorie": "sceptre",
  "rarete": "legendaire",
  "harmonisation": true,
  "harmonisation_detail": null,
  "type": "sceptre",
  "effets": [],
  "poids": "0.000",
  "prix_estime": "0.00",
  "source": "SRD",
  "image": null,
  "resume": "Masse magique +2 offrant des avantages de perception/survie en wastelands et protection contre aberrations/fiends avec capacités de smite amélioré.",
  "combat": {
    "bonus": 2,
    "bonus_ca": 0,
    "degats_bonus": "",
    "type_degats_bonus": "",
    "pv_soins": "",
    "charges": null,
    "effets": [
      "Avantage aux tests de Perception et Survie en badlands/wastelands",
      "Avantage aux jets de sauvegarde contre charme par aberrations/fiends",
      "Divine Smite : dés de dégâts radiants maximisés contre aberrations/fiends (1/aube)"
    ]
  }
}