{
  "slug": "staff-of-the-artisan",
  "nom": "Bâton de l'Artisan",
  "nom_original": "Staff of the Artisan",
  "categorie": "baton",
  "rarete": "rare",
  "harmonisation": false,
  "harmonisation_detail": null,
  "type": "baton",
  "effets": [],
  "poids": "0.000",
  "prix_estime": "0.00",
  "source": "SRD",
  "image": null,
  "resume": "Bâton magique +2 permettant de créer des objets inanimés et de lancer des sorts de création et d'animation.",
  "combat": {
    "bonus": 2,
    "bonus_ca": 0,
    "degats_bonus": "",
    "type_degats_bonus": "",
    "pv_soins": "",
    "charges": 10,
    "effets": [
      "+2 attaque et dégâts",
      "Création d'objet inanimé (2 charges, max 3 pieds, 10 livres)",
      "Sorts : Animer les objets (5), Fabrication (4), Disque flottant (1), Réparation gratuite"
    ]
  }
}